dsap/__init__.py
dsap/bsts/structs/avlt.py
dsap/bsts/structs/rbt.py
dsap/graphs/mst/kruskal.py
dsap/graphs/mst/make_tree.py
dsap/graphs/mst/prim.py
dsap/graphs/pathfinding/astar.py
dsap/graphs/pathfinding/bellman_ford.py
dsap/graphs/pathfinding/dijkstra.py
dsap/graphs/pathfinding/floyd_warshall.py
dsap/graphs/sorting/topological_sorting.py
dsap/graphs/structs/graph.py
dsap/hash_tables/structs/hash_table.py
dsap/heaps/structs/kbh.py
dsap/heaps/structs/kfh.py
dsap/heaps/structs/kkah.py
dsap/heaps/structs/kmmh.py
dsap/linked_lists/structs/cdll.py
dsap/linked_lists/structs/csll.py
dsap/linked_lists/structs/dll.py
dsap/linked_lists/structs/sll.py
dsap/misc/cp_combinations.py
dsap/misc/cp_permutations.py
dsap/misc/segment_tree.py
dsap/queues/structs/deque.py
dsap/queues/structs/priority_queue.py
dsap/stacks/structs/stack.py
dsap-1.0.1.dist-info/METADATA
dsap-1.0.1.dist-info/WHEEL
dsap-1.0.1.dist-info/licenses/LICENSE
dsap-1.0.1.dist-info/RECORD
